ctrate/__init__.py
ctrate/cli.py
ctrate-0.0.1.dist-info/LICENSE
ctrate-0.0.1.dist-info/METADATA
ctrate-0.0.1.dist-info/WHEEL
ctrate-0.0.1.dist-info/entry_points.txt
ctrate-0.0.1.dist-info/top_level.txt
ctrate-0.0.1.dist-info/RECORD
